{
  "_id": 67,
  "key": "067",
  "name": "Digtoise",
  "stats": {
    "hp": 80,
    "attack": {
      "melee": 80,
      "ranged": 95
    },
    "defense": 120,
    "speed": {
      "ride": 420,
      "run": 300,
      "walk": 120
    },
    "stamina": 100,
    "support": 100,
    "food": 5
  },
  "type": [
    "Ground"
  ],
  "work": [
    {
      "type": "Mining",
      "level": 3
    }
  ],
  "drops": [
    "Ore",
    "High Quality Pal Oil"
  ],
  "ability": {
    "name": "Drill Crusher",
    "description": "When activated, performs Shell Spin, follows the player while spinning, and mines ores efficiently.",
    "tech": null
  },
  "asset": "DrillGame",
  "genus": "fourlegged",
  "rarity": 5,
  "price": 2980,
  "size": "m",
  "description": "A walking contradiction, possessing the strongest shell and the only drill capable of piercing it. \"Digtoise's Fable\" is a popular children's tale.",
  "skills": [
    {
      "level": 1,
      "name": "Aqua Gun",
      "type": "Water",
      "cooldown": 4,
      "power": 40,
      "description": "Hurls a ball of water straight at an enemy.\n"
    },
    {
      "level": 7,
      "name": "Stone Blast",
      "type": "Ground",
      "cooldown": 10,
      "power": 55,
      "description": "Fires a barrage of stones forward.\n"
    },
    {
      "level": 15,
      "name": "Shell Spin",
      "type": "Ground",
      "cooldown": 9,
      "power": 65,
      "description": "Digtoise's exclusive skill. Moves while spinning its whole body at high speeds. Drills through enemies, dealing continuous damage.\n"
    },
    {
      "level": 22,
      "name": "Stone Cannon",
      "type": "Ground",
      "cooldown": 15,
      "power": 70,
      "description": "Digs up a boulder and hurls it at an enemy.\n"
    },
    {
      "level": 30,
      "name": "Sand Tornado",
      "type": "Ground",
      "cooldown": 18,
      "power": 80,
      "description": "Generates two sand tornadoes on either side before launching them at an enemy.\n"
    },
    {
      "level": 40,
      "name": "Aqua Burst",
      "type": "Water",
      "cooldown": 30,
      "power": 100,
      "description": "Creates a giant ball of water and hurls it at an enemy.\n"
    },
    {
      "level": 50,
      "name": "Rock Lance",
      "type": "Ground",
      "cooldown": 55,
      "power": 150,
      "description": "Generates a sharp rock spear under an enemy.\n"
    }
  ]
}