{
  "_id": 158,
  "key": "totodile",
  "name": {
    "english": "Totodile",
    "spanish": "Totodile",
    "italian": "Totodile",
    "japanese": "ワニノコ",
    "chinese": "小锯鳄",
    "korean": "",
    "german": "Karnimani",
    "french": "Kaiminus"
  },
  "pokedexNumber": {
    "crystal": 7,
    "gold-silver": 7
  },
  "type": {
    "one": "Water"
  },
  "abilities": {
    "one": {
      "name": "Torrent",
      "id": 67
    },
    "hidden": {
      "name": "Sheer Force",
      "id": 125
    }
  },
  "baseStats": {
    "hp": 50,
    "atk": 65,
    "def": 64,
    "spatk": 44,
    "spdef": 48,
    "spd": 43,
    "total": 314
  },
  "info": {
    "height": "0.6 m (2′00″)",
    "weight": "9.5 kg (20.9 lbs)"
  },
  "gender": {
    "male": "87.5%",
    "female": "12.5%",
    "genderless": false
  },
  "evolution": 56,
  "generation": 2,
  "evs": {
    "atk": 1
  },
  "eggGroups": [
    "Monster",
    "Water 1"
  ],
  "species": "Big Jaw Pokémon",
  "catchRate": 45,
  "baseFriendship": 50,
  "baseExp": 63,
  "growthRate": "Medium Slow",
  "eggCycles": 20,
  "nameOrigin": {
    "tot": "a small child",
    "crocodile": "a species of reptile"
  },
  "pokedexEntries": {
    "Totodile": [
      {
        "game": "gold",
        "desc": "Its well-developed jaws are powerful and capable of crushing anything. Even its trainer must be careful."
      },
      {
        "game": "silver",
        "desc": "It is small but rough and tough. It won’t hesitate to take a bite out of anything that moves."
      },
      {
        "game": "crystal",
        "desc": "This rough critter chomps at any moving object it sees. Turning your back on it is not recommended."
      },
      {
        "game": "ruby-sapphire",
        "desc": "Despite the smallness of its body, TOTODILE’s jaws are very powerful. While the POKéMON may think it is just playfully nipping, its bite has enough power to cause serious injury."
      },
      {
        "game": "fire-red",
        "desc": "It is small but rough and tough. It won’t hesitate to take a bite out of anything that moves."
      },
      {
        "game": "leaf-green",
        "desc": "Its well-developed jaws are powerful and capable of crushing anything. Even its TRAINER must be careful."
      },
      {
        "game": "emerald",
        "desc": "Despite its small body, TOTODILE’s jaws are very powerful. While it may think it is just playfully nipping, its bite has enough strength to cause serious injury."
      },
      {
        "game": "diamond-pearl-platinum",
        "desc": "It has the habit of biting anything with its developed jaws. Even its Trainer needs to be careful."
      },
      {
        "game": "heart-gold",
        "desc": "Its powerful, well-developed jaws are capable of crushing anything. Even its Trainer must be careful."
      },
      {
        "game": "soul-silver",
        "desc": "It is small but rough and tough. It won’t hesitate to take a bite out of anything that moves."
      },
      {
        "game": "black-white-black-2-white-2",
        "desc": "It has the habit of biting anything with its developed jaws. Even its Trainer needs to be careful."
      },
      {
        "game": "x",
        "desc": "It is small but rough and tough. It won’t hesitate to take a bite out of anything that moves."
      },
      {
        "game": "y",
        "desc": "Its powerful, well-developed jaws are capable of crushing anything. Even its Trainer must be careful."
      },
      {
        "game": "omega-ruby-alpha-sapphire",
        "desc": "Despite the smallness of its body, Totodile’s jaws are very powerful. While the Pokémon may think it is just playfully nipping, its bite has enough power to cause serious injury."
      },
      {
        "game": "brilliant-diamond-shining-pearl",
        "desc": "It has a habit of biting everything with its well-developed jaws. Even its Trainer needs to be careful."
      }
    ]
  }
}