{
  "_id": 174,
  "key": "igglybuff",
  "name": {
    "english": "Igglybuff",
    "spanish": "Igglybuff",
    "italian": "Igglybuff",
    "japanese": "ププリン",
    "chinese": "宝宝丁",
    "korean": "",
    "german": "Fluffeluff",
    "french": "Toudoudou"
  },
  "pokedexNumber": {
    "scarlet-violet": 59,
    "isle-of-armor": 11,
    "crystal": 43,
    "gold-silver": 43
  },
  "type": {
    "one": "Normal",
    "two": "Fairy"
  },
  "abilities": {
    "one": {
      "name": "Cute Charm",
      "id": 56
    },
    "two": {
      "name": "Competitive",
      "id": 172
    },
    "hidden": {
      "name": "Friend Guard",
      "id": 132
    }
  },
  "baseStats": {
    "hp": 90,
    "atk": 30,
    "def": 15,
    "spatk": 40,
    "spdef": 20,
    "spd": 15,
    "total": 210
  },
  "info": {
    "height": "0.3 m (1′00″)",
    "weight": "1.0 kg (2.2 lbs)"
  },
  "gender": {
    "male": "25%",
    "female": "75%",
    "genderless": false
  },
  "evolution": 16,
  "generation": 2,
  "evs": {},
  "eggGroups": [
    "Undiscovered"
  ],
  "species": "Balloon Pokémon",
  "catchRate": 170,
  "baseFriendship": 50,
  "baseExp": 42,
  "growthRate": "Fast",
  "eggCycles": 10,
  "nameOrigin": {
    "jiggly/wiggly": "from later evolutions Jigglypuff/Wigglytuff",
    "buff": "to shine"
  },
  "pokedexEntries": {
    "Igglybuff": [
      {
        "game": "gold",
        "desc": "It has a very soft body. If it starts to roll, it will bounce all over and be impossible to stop."
      },
      {
        "game": "silver",
        "desc": "Its extremely flexible and elastic body makes it bounce continuously--anytime, anywhere."
      },
      {
        "game": "crystal",
        "desc": "Instead of walking with its short legs, it moves around by bouncing on its soft, tender body."
      },
      {
        "game": "ruby",
        "desc": "IGGLYBUFF’s vocal chords are not sufficiently developed. It would hurt its throat if it were to sing too much. This POKéMON gargles with freshwater from a clean stream."
      },
      {
        "game": "sapphire",
        "desc": "IGGLYBUFF has a soft and plushy body that feels very much like a marshmallow. From this body wafts a gently sweet fragrance that soothes and calms the emotions of its foes."
      },
      {
        "game": "fire-red",
        "desc": "Its extremely flexible and elastic body makes it bounce continuously--anytime, anywhere."
      },
      {
        "game": "leaf-green",
        "desc": "It has a very soft body. If it starts to roll, it will bounce all over and be impossible to stop."
      },
      {
        "game": "emerald",
        "desc": "Its soft and pliable body is very bouncy. When it sings continuously with all its might, its body steadily turns a deepening pink color."
      },
      {
        "game": "diamond-pearl-platinum",
        "desc": "It has a soft and bouncy body. Once it starts bouncing, it becomes impossible to stop."
      },
      {
        "game": "heart-gold",
        "desc": "It has a very soft body. If it starts to roll, it will bounce all over and be impossible to stop."
      },
      {
        "game": "soul-silver",
        "desc": "Its extremely flexible and elastic body makes it bounce continuously--anytime, anywhere."
      },
      {
        "game": "black-white",
        "desc": "It has a soft and bouncy body. Once it starts bouncing, it becomes impossible to stop."
      },
      {
        "game": "black-2-white-2",
        "desc": "Its body has a faintly sweet scent and is bouncy and soft. If it bounces even once, it cannot stop."
      },
      {
        "game": "x",
        "desc": "Instead of walking with its short legs, it moves around by bouncing on its soft, tender body."
      },
      {
        "game": "y",
        "desc": "It has a very soft body. If it starts to roll, it will bounce all over and be impossible to stop."
      },
      {
        "game": "omega-ruby",
        "desc": "Igglybuff’s vocal cords are not sufficiently developed. It would hurt its throat if it were to sing too much. This Pokémon gargles with freshwater from a clean stream."
      },
      {
        "game": "alpha-sapphire",
        "desc": "Igglybuff has a soft and plushy body that feels very much like a marshmallow. From this body wafts a gently sweet fragrance that soothes and calms the emotions of its foes."
      },
      {
        "game": "sun",
        "desc": "It likes to sing but is not yet good at it. With praise and encouragement, it will get better little by little."
      },
      {
        "game": "moon",
        "desc": "It moves by bouncing along. As it moves a lot, it sweats, and its body gives off a sweet aroma."
      },
      {
        "game": "ultra-sun",
        "desc": "It’s always practicing its singing because it wants to improve. Even when it’s asleep, it keeps singing in its dreams!"
      },
      {
        "game": "ultra-moon",
        "desc": "Left to its own devices, it will constantly practice singing. You should make it take a break so it doesn’t hurt its throat."
      },
      {
        "game": "sword",
        "desc": "Igglybuff loves to sing. Its marshmallow-like body gives off a faint sweet smell."
      },
      {
        "game": "shield",
        "desc": "Taking advantage of the softness of its body, Igglybuff moves as if bouncing. Its body turns a deep pink when its temperature rises."
      },
      {
        "game": "brilliant-diamond-shining-pearl",
        "desc": "It has a soft and bouncy body. Once it starts bouncing, it becomes impossible to stop."
      }
    ]
  }
}