{
  "_id": 686,
  "key": "inkay",
  "name": {
    "english": "Inkay",
    "spanish": "Inkay",
    "italian": "Inkay",
    "japanese": "マーイーカ",
    "chinese": "好啦鱿",
    "korean": "",
    "german": "Iscalar",
    "french": "Sepiatop"
  },
  "pokedexNumber": {
    "sword-shield": 290,
    "isle-of-armor": 108
  },
  "type": {
    "one": "Dark",
    "two": "Psychic"
  },
  "abilities": {
    "one": {
      "name": "Contrary",
      "id": 126
    },
    "two": {
      "name": "Suction Cups",
      "id": 21
    },
    "hidden": {
      "name": "Infiltrator",
      "id": 151
    }
  },
  "baseStats": {
    "hp": 53,
    "atk": 54,
    "def": 53,
    "spatk": 37,
    "spdef": 46,
    "spd": 45,
    "total": 288
  },
  "info": {
    "height": "0.4 m (1′04″)",
    "weight": "3.5 kg (7.7 lbs)"
  },
  "gender": {
    "male": "50%",
    "female": "50%",
    "genderless": false
  },
  "evolution": 238,
  "generation": 6,
  "evs": {
    "atk": 1
  },
  "eggGroups": [
    "Water 1",
    "Water 2"
  ],
  "species": "Revolving Pokémon",
  "catchRate": 190,
  "baseFriendship": 50,
  "baseExp": 58,
  "growthRate": "Medium Fast",
  "eggCycles": 20,
  "nameOrigin": {
    "ink": "dark fluid ejected by squid",
    "okay": "agreement, acceptance"
  },
  "pokedexEntries": {
    "Inkay": [
      {
        "game": "x-omega-ruby",
        "desc": "Opponents who stare at the flashing of the light-emitting spots on its body become dazed and lose their will to fight."
      },
      {
        "game": "y-alpha-sapphire",
        "desc": "It flashes the light-emitting spots on its body, which drains its opponent’s will to fight. It takes the opportunity to scuttle away and hide."
      },
      {
        "game": "ultra-sun",
        "desc": "It draws prey near with its blinking lights and then wraps them up in its long tentacles and holds them in place."
      },
      {
        "game": "ultra-moon",
        "desc": "When exchanging information with others of its kind, it flashes the light-emitting spots on its body in a complex rhythm."
      },
      {
        "game": "sword",
        "desc": "It spins while making its luminescent spots flash. These spots allow it to communicate with others by using different patterns of light."
      },
      {
        "game": "shield",
        "desc": "By exposing foes to the blinking of its luminescent spots, Inkay demoralizes them, and then it seizes the chance to flee."
      }
    ]
  }
}