{
  "_id": 898,
  "key": "calyrex",
  "name": {
    "english": "Calyrex",
    "spanish": "Calyrex",
    "italian": "Calyrex",
    "japanese": "バドレックス",
    "chinese": "蕾冠王",
    "korean": "",
    "german": "Coronospa",
    "french": "Sylveroy"
  },
  "pokedexNumber": {
    "crown-tundra": 210
  },
  "type": {
    "one": "Psychic",
    "two": "Grass"
  },
  "abilities": {
    "one": {
      "name": "Unnerve",
      "id": 127
    }
  },
  "baseStats": {
    "hp": 100,
    "atk": 80,
    "def": 80,
    "spatk": 80,
    "spdef": 80,
    "spd": 80,
    "total": 500
  },
  "info": {
    "height": "2.4 m (7′10″)",
    "weight": "53.6 kg (118.2 lbs)"
  },
  "gender": {
    "male": "",
    "female": "",
    "genderless": true
  },
  "evolution": null,
  "generation": 8,
  "evs": {},
  "eggGroups": [
    null
  ],
  "species": "King Pokémon",
  "catchRate": 3,
  "baseFriendship": 100,
  "baseExp": 250,
  "growthRate": "Slow",
  "eggCycles": 120,
  "nameOrigin": {},
  "pokedexEntries": {
    "Calyrex": [
      {
        "game": "sword",
        "desc": "Calyrex is a merciful Pokémon, capable of providing healing and blessings. It reigned over the Galar region in times of yore."
      },
      {
        "game": "shield",
        "desc": "Calyrex is known in legend as a king that ruled over Galar in ancient times. It has the power to cause hearts to mend and plants to spring forth."
      }
    ],
    "Ice Rider": [
      {
        "game": "sword",
        "desc": "According to lore, this Pokémon showed no mercy to those who got in its way, yet it would heal its opponents’ wounds after battle."
      },
      {
        "game": "shield",
        "desc": "It’s said that this Pokémon once moved a large forest—and all the Pokémon living there—to a new location overnight."
      }
    ],
    "Shadow Rider": [
      {
        "game": "sword",
        "desc": "It’s said that Calyrex and a Pokémon that had bonded with it ran all across the Galar region to bring green to the wastelands."
      },
      {
        "game": "shield",
        "desc": "Legend says that by using its power to see all events from past to future, this Pokémon saved the creatures of a forest from a meteorite strike."
      }
    ]
  }
}