{
  "_id": 931.1,
  "key": "squawkabilly",
  "name": {
    "english": "Squawkabilly"
  },
  "pokedexNumber": {
    "scarlet-violet": 113
  },
  "type": {
    "one": "Normal",
    "two": "Flying"
  },
  "abilities": {
    "one": {
      "name": "Intimidate",
      "id": 22
    },
    "two": {
      "name": "Hustle",
      "id": 55
    },
    "hidden": {
      "name": "Guts",
      "id": 62
    }
  },
  "baseStats": {
    "hp": 82,
    "atk": 96,
    "def": 51,
    "spatk": 45,
    "spdef": 51,
    "spd": 92,
    "total": 417
  },
  "info": {
    "height": "0.6 m (2′00″)",
    "weight": "2.4 kg (5.3 lbs)"
  },
  "gender": {
    "male": "50%",
    "female": "50%",
    "genderless": false
  },
  "evolution": 0,
  "evs": {},
  "eggGroups": [
    null
  ],
  "species": "Parrot Pokémon",
  "catchRate": 190,
  "baseFriendship": 50,
  "growthRate": "Erratic",
  "eggCycles": 15,
  "nameOrigin": {
    "squawk": "the loud screech a bird makes",
    "rockabilly": "genre of rock music"
  },
  "pokedexEntries": {
    "Blue Plumage": [
      {
        "game": "scarlet",
        "desc": "The largest of their flocks can contain more than 50 individuals. They fly around towns and forests, searching for food and making a racket."
      },
      {
        "game": "violet",
        "desc": "Blue-feathered Squawkabilly view their green-feathered counterparts as rivals, since the latter make up the largest, most powerful groups."
      }
    ]
  }
}